{
  "ids": [
    "f86a3881b8ed",
    "8ea695daf6b6",
    "9c58e03b97a8",
    "9c1ab9d061e6",
    "c86efc4aa36b",
    "f79acfa9913e",
    "84b9435b95b6",
    "748df4451f12",
    "73d50a71a8dd",
    "a6b559f285a2",
    "1f67f8b8243c",
    "2d1c06162aa1",
    "5878daeec25a",
    "7cea0cd918fc",
    "1a4cd2701e93",
    "c4748915001a",
    "1426c1e04756",
    "9a76b37801e6",
    "e38fdd81287c",
    "12da41a1edbf",
    "03bc0dbae8cc",
    "8f8eb3525a7f",
    "5f3f308e9862",
    "700885173683",
    "63dc48ffaf86",
    "32fdb5f998e3",
    "b5832cd9f2a3",
    "e5ed564e9f1c",
    "8287aa7feb1a",
    "16d6c728d1cb"
  ],
  "items": [
    {
      "id": "5878daeec25a",
      "title": "《秘密花园园丁邀请函》",
      "link": "https://linux.do/t/topic/847468"
    },
    {
      "id": "9a76b37801e6",
      "title": "请不要把互联网上的戾气带来这里！",
      "link": "https://linux.do/t/topic/482293"
    },
    {
      "id": "f86a3881b8ed",
      "title": "HLOOL纯GPT公益站，重新开通",
      "link": "https://linux.do/t/topic/2489666"
    },
    {
      "id": "8f8eb3525a7f",
      "title": "超200万粉丝网红诋毁袁隆平成果，遭痛批",
      "link": "https://linux.do/t/topic/2488728"
    },
    {
      "id": "2d1c06162aa1",
      "title": "兄弟们提不起兴趣怎么办",
      "link": "https://linux.do/t/topic/2489638"
    },
    {
      "id": "63dc48ffaf86",
      "title": "「君の公益」重新限制为三级使用",
      "link": "https://linux.do/t/topic/2452094"
    },
    {
      "id": "8287aa7feb1a",
      "title": "佬友们硬盘分几个区？",
      "link": "https://linux.do/t/topic/2488840"
    },
    {
      "id": "16d6c728d1cb",
      "title": "【CHY公益站】GLM-5.2扩容",
      "link": "https://linux.do/t/topic/2487986"
    },
    {
      "id": "1426c1e04756",
      "title": "注册了个 0penAI.net 恶搞一下",
      "link": "https://linux.do/t/topic/2489188"
    },
    {
      "id": "c86efc4aa36b",
      "title": "或许我们可以在推特上批评克劳德的封号政策",
      "link": "https://linux.do/t/topic/2488740"
    },
    {
      "id": "e5ed564e9f1c",
      "title": "为什么说人赚不到认知以外的钱",
      "link": "https://linux.do/t/topic/2488510"
    },
    {
      "id": "9c1ab9d061e6",
      "title": "分享一个免费使用顶级模型的网站",
      "link": "https://linux.do/t/topic/2489550"
    },
    {
      "id": "5f3f308e9862",
      "title": "小米MIMO 吃相太太太难看了",
      "link": "https://linux.do/t/topic/2489217"
    },
    {
      "id": "a6b559f285a2",
      "title": "（已撤离勿点）纯水贴！！！",
      "link": "https://linux.do/t/topic/2489512"
    },
    {
      "id": "73d50a71a8dd",
      "title": "最最喜欢Neo了！真的搞得我好爽啊啊啊啊！！！",
      "link": "https://linux.do/t/topic/2488053"
    },
    {
      "id": "84b9435b95b6",
      "title": "论短视频——浅浅可爱地翻译一篇英语阅读理解~",
      "link": "https://linux.do/t/topic/2489634"
    },
    {
      "id": "748df4451f12",
      "title": "来还债了，PackyCode 在 L 站的一年，话不多说抽个 macmini",
      "link": "https://linux.do/t/topic/2448069"
    },
    {
      "id": "9c58e03b97a8",
      "title": "【月城公益站】周日再发一波CDK",
      "link": "https://linux.do/t/topic/2488313"
    },
    {
      "id": "e38fdd81287c",
      "title": "现在读书性价比是否还有那么高呢",
      "link": "https://linux.do/t/topic/2487552"
    },
    {
      "id": "8ea695daf6b6",
      "title": "【求助】Windows电脑变成Linux系统",
      "link": "https://linux.do/t/topic/2488177"
    },
    {
      "id": "b5832cd9f2a3",
      "title": "gemini王朝了吗",
      "link": "https://linux.do/t/topic/2489553"
    },
    {
      "id": "c4748915001a",
      "title": "polymarket消息,智谱最新模型在发现安全漏洞的能力上已接近mythos",
      "link": "https://linux.do/t/topic/2488390"
    },
    {
      "id": "7cea0cd918fc",
      "title": "不知道在整理什么的汇总整理贴",
      "link": "https://linux.do/t/topic/2488899"
    },
    {
      "id": "700885173683",
      "title": "不多说，快抢注agent邮箱去",
      "link": "https://linux.do/t/topic/2480581"
    },
    {
      "id": "f79acfa9913e",
      "title": "【公益站】猫猫公益站-众人拾柴火焰高",
      "link": "https://linux.do/t/topic/2485789"
    },
    {
      "id": "1f67f8b8243c",
      "title": "「香香甜甜小蛋糕~」这一期是裸腿w",
      "link": "https://linux.do/t/topic/2487684"
    },
    {
      "id": "1a4cd2701e93",
      "title": "【公益站】猫猫公益站–渠道是老黄的免费key",
      "link": "https://linux.do/t/topic/2485331"
    },
    {
      "id": "32fdb5f998e3",
      "title": "教育邮箱 (.edu) 还能解锁哪些专属优惠和免费资源",
      "link": "https://linux.do/t/topic/2489407"
    },
    {
      "id": "03bc0dbae8cc",
      "title": "观电影《四渡》，忍不住吐槽",
      "link": "https://linux.do/t/topic/2487946"
    },
    {
      "id": "12da41a1edbf",
      "title": "一瞬景观:破晓",
      "link": "https://linux.do/t/topic/2488792"
    }
  ]
}